pybcf/__init__.py
pybcf/reader.cp312-win_amd64.pyd
pybcf-1.3.7.dist-info/licenses/LICENSE.txt
pybcf-1.3.7.dist-info/METADATA
pybcf-1.3.7.dist-info/WHEEL
pybcf-1.3.7.dist-info/top_level.txt
pybcf-1.3.7.dist-info/RECORD
