Metadata-Version: 2.4
Name: pybcf
Version: 1.3.7
Summary: Package for loading data from bcf files
Home-page: https://github.com/jeremymcrae/pybcf
Author: Jeremy McRae
Author-email: jmcrae@illumina.com
License: MIT
Classifier: Development Status :: 4 - Beta
Classifier: Topic :: Scientific/Engineering :: Bio-Informatics
License-File: LICENSE.txt
Requires-Dist: numpy
Provides-Extra: test
Requires-Dist: pysam; extra == "test"
Dynamic: author
Dynamic: author-email
Dynamic: classifier
Dynamic: description
Dynamic: description-content-type
Dynamic: home-page
Dynamic: license
Dynamic: license-file
Dynamic: provides-extra
Dynamic: requires-dist
Dynamic: summary
